LICENSE
README.rst
setup.py
nyoibo/__init__.py
nyoibo/exceptions.py
nyoibo/fields.c
nyoibo/utils.py
nyoibo.egg-info/PKG-INFO
nyoibo.egg-info/SOURCES.txt
nyoibo.egg-info/dependency_links.txt
nyoibo.egg-info/top_level.txt
nyoibo/entities/__init__.py
nyoibo/entities/entity.c
nyoibo/entities/meta_entity.py
tests/__init__.py
tests/test_entity.py
tests/test_entity_inheritance.py
tests/test_field_validations.py
tests/test_fields.py