Metadata-Version: 2.1
Name: nyoibo
Version: 0.6.0
Summary: Implement attributes accessors in an easy way
Home-page: https://github.com/pity7736/nyoibo
Author: Julián Cortés
Author-email: julian.cortes77@protonmail.com
Keywords: accessors private
Classifier: Development Status :: 4 - Beta
Classifier: Intended Audience :: Developers
Classifier: License :: OSI Approved :: GNU General Public License v3 (GPLv3)
Classifier: Natural Language :: English
Classifier: Operating System :: OS Independent
Classifier: Programming Language :: Python :: 3 :: Only
Classifier: Programming Language :: Python :: 3.9
Classifier: Programming Language :: Python :: 3.10
Classifier: Programming Language :: Python :: 3.11
Classifier: Topic :: Software Development
Classifier: Topic :: Utilities
Classifier: Typing :: Typed
Requires-Python: >=3.9
License-File: LICENSE
